Metadata-Version: 1.0
Name: wxy-csv
Version: 0.0.1
Summary: 封装一些csv的操作方法
Home-page: https://gitee.com/wang_xing_yuan/wxy_csv.git
Author: cooper_wang
Author-email: UNKNOWN
License: MIT
Platform: UNKNOWN
